[
    {
        "name": "Levis",
        "id": 155624,
        "brand_name": "",
        "size": [
            "XS",
            "S",
            "M",
            "L",
            "XL",
            "XXL"
        ],
        "mrp": "2650",
        "price": "1999",
        "discount": "25%",
        "available_piece": 10,
        "is_visible": true,
        "images": [
            "/assets/shirt1.jpg",
            "",
            "",
            ""
        ],
        "out_of_stock": false,
        "rating": 5,
        "reviews": 125,
        "category": "formal",
        "gender": "male",
        "color": "blue",
        "description": "Lorem ipsum dolor sit amet. Et neque galisum eos ipsum autem est alias neque sed dolorem porro non autem ratione non distinctio quibusdam non sunt quae. Vel Quis error et officia cupiditate est ipsam assumenda qui consequuntur dolores et repudiandae necessitatibus aut internos possimus ut sunt deserunt! Sit quaerat assumenda ut nostrum quia quo ipsa quasi aut animi numquam.Sit provident illum aut sapiente quis et odio maxime et animi doloribus ut quisquam error. ",
        "isSidebar": true
    },
    {
        "name": "Team Spirit",
        "id": 155625,
        "brand_name": "",
        "size": [
            "XS",
            "S",
            "M",
            "L",
            "XL",
            "XXL"
        ],
        "mrp": "1999",
        "price": "1499",
        "discount": "25%",
        "available_piece": 10,
        "is_visible": true,
        "images": [
            "/assets/tshirt1.jpg",
            "",
            "",
            ""
        ],
        "out_of_stock": false,
        "rating": 4,
        "reviews": 55,
        "category": "casual",
        "gender": "male",
        "color": "pink",
        "description": "Lorem ipsum dolor sit amet. Et neque galisum eos ipsum autem est alias neque sed dolorem porro non autem ratione non distinctio quibusdam non sunt quae. Vel Quis error et officia cupiditate est ipsam assumenda qui consequuntur dolores et repudiandae necessitatibus aut internos possimus ut sunt deserunt! Sit quaerat assumenda ut nostrum quia quo ipsa quasi aut animi numquam.Sit provident illum aut sapiente quis et odio maxime et animi doloribus ut quisquam error. ",
        "isSidebar": true
    },
    {
        "name": "Netplay",
        "id": 155626,
        "brand_name": "",
        "size": [
            "XS",
            "S",
            "M",
            "L",
            "XL",
            "XXL"
        ],
        "mrp": "10999",
        "price": "7999",
        "discount": "25%",
        "available_piece": 10,
        "is_visible": true,
        "images": [
            "/assets/suit1.jpg",
            "",
            "",
            ""
        ],
        "out_of_stock": false,
        "rating": 3,
        "reviews": 15,
        "category": "western",
        "gender": "male",
        "color": "blue",
        "description": "Lorem ipsum dolor sit amet. Et neque galisum eos ipsum autem est alias neque sed dolorem porro non autem ratione non distinctio quibusdam non sunt quae. Vel Quis error et officia cupiditate est ipsam assumenda qui consequuntur dolores et repudiandae necessitatibus aut internos possimus ut sunt deserunt! Sit quaerat assumenda ut nostrum quia quo ipsa quasi aut animi numquam.Sit provident illum aut sapiente quis et odio maxime et animi doloribus ut quisquam error. ",
        "isSidebar": true
    },
    {
        "name": "Monte Carlo",
        "id": 155627,
        "brand_name": "",
        "size": [
            "XS",
            "S",
            "M",
            "L",
            "XL",
            "XXL"
        ],
        "mrp": "7999",
        "price": "5999",
        "discount": "25%",
        "available_piece": 10,
        "is_visible": true,
        "images": [
            "/assets/coat1.jpg",
            "",
            "",
            ""
        ],
        "out_of_stock": false,
        "rating": 5,
        "reviews": 120,
        "category": "formal",
        "gender": "male",
        "color": "black",
        "description": "Lorem ipsum dolor sit amet. Et neque galisum eos ipsum autem est alias neque sed dolorem porro non autem ratione non distinctio quibusdam non sunt quae. Vel Quis error et officia cupiditate est ipsam assumenda qui consequuntur dolores et repudiandae necessitatibus aut internos possimus ut sunt deserunt! Sit quaerat assumenda ut nostrum quia quo ipsa quasi aut animi numquam.Sit provident illum aut sapiente quis et odio maxime et animi doloribus ut quisquam error. ",
        "isSidebar": true
    },
    {
        "name": "Red tape",
        "id": 155628,
        "brand_name": "",
        "size": [
            "XS",
            "S",
            "M",
            "L",
            "XL",
            "XXL"
        ],
        "mrp": "1999",
        "price": "1499",
        "discount": "25%",
        "available_piece": 10,
        "is_visible": true,
        "images": [
            "/assets/kurta1.jpg",
            "",
            "",
            ""
        ],
        "out_of_stock": false,
        "rating": 4,
        "reviews": 105,
        "category": "ethnic",
        "gender": "male",
        "color": "orange",
        "description": "Lorem ipsum dolor sit amet. Et neque galisum eos ipsum autem est alias neque sed dolorem porro non autem ratione non distinctio quibusdam non sunt quae. Vel Quis error et officia cupiditate est ipsam assumenda qui consequuntur dolores et repudiandae necessitatibus aut internos possimus ut sunt deserunt! Sit quaerat assumenda ut nostrum quia quo ipsa quasi aut animi numquam.Sit provident illum aut sapiente quis et odio maxime et animi doloribus ut quisquam error. ",
        "isSidebar": true
    },
    {
        "name": "BIBA",
        "id": 155629,
        "brand_name": "",
        "size": [
            "XS",
            "S",
            "M",
            "L",
            "XL",
            "XXL"
        ],
        "mrp": "3499",
        "price": "2499",
        "discount": "25%",
        "available_piece": 10,
        "is_visible": true,
        "images": [
            "/assets/kurti1.jpg",
            "",
            "",
            ""
        ],
        "out_of_stock": false,
        "rating": 5,
        "reviews": 125,
        "category": "ethnic",
        "gender": "female",
        "color": "green",
        "description": "Lorem ipsum dolor sit amet. Et neque galisum eos ipsum autem est alias neque sed dolorem porro non autem ratione non distinctio quibusdam non sunt quae. Vel Quis error et officia cupiditate est ipsam assumenda qui consequuntur dolores et repudiandae necessitatibus aut internos possimus ut sunt deserunt! Sit quaerat assumenda ut nostrum quia quo ipsa quasi aut animi numquam.Sit provident illum aut sapiente quis et odio maxime et animi doloribus ut quisquam error. ",
        "isSidebar": true
    },
    {
        "name": "Monte Carlo",
        "id": 155630,
        "brand_name": "",
        "size": [
            "XS",
            "S",
            "M",
            "L",
            "XL",
            "XXL"
        ],
        "mrp": "6500",
        "price": "4999",
        "discount": "25%",
        "available_piece": 10,
        "is_visible": true,
        "images": [
            "/assets/formals1.jpg",
            "",
            "",
            ""
        ],
        "out_of_stock": false,
        "rating": 4,
        "reviews": 55,
        "category": "formal",
        "gender": "female",
        "color": "black",
        "description": "Lorem ipsum dolor sit amet. Et neque galisum eos ipsum autem est alias neque sed dolorem porro non autem ratione non distinctio quibusdam non sunt quae. Vel Quis error et officia cupiditate est ipsam assumenda qui consequuntur dolores et repudiandae necessitatibus aut internos possimus ut sunt deserunt! Sit quaerat assumenda ut nostrum quia quo ipsa quasi aut animi numquam.Sit provident illum aut sapiente quis et odio maxime et animi doloribus ut quisquam error. ",
        "isSidebar": true
    },
    {
        "name": "Zara",
        "id": 155631,
        "brand_name": "",
        "size": [
            "XS",
            "S",
            "M",
            "L",
            "XL",
            "XXL"
        ],
        "mrp": "2699",
        "price": "1999",
        "discount": "25%",
        "available_piece": 10,
        "is_visible": true,
        "images": [
            "/assets/dress1.jpg",
            "",
            "",
            ""
        ],
        "out_of_stock": false,
        "rating": 5,
        "reviews": 250,
        "category": "western",
        "gender": "female",
        "color": "white",
        "description": "Lorem ipsum dolor sit amet. Et neque galisum eos ipsum autem est alias neque sed dolorem porro non autem ratione non distinctio quibusdam non sunt quae. Vel Quis error et officia cupiditate est ipsam assumenda qui consequuntur dolores et repudiandae necessitatibus aut internos possimus ut sunt deserunt! Sit quaerat assumenda ut nostrum quia quo ipsa quasi aut animi numquam.Sit provident illum aut sapiente quis et odio maxime et animi doloribus ut quisquam error. ",
        "isSidebar": true
    },
    {
        "name": "Team Spirit",
        "id": 155632,
        "brand_name": "",
        "size": [
            "XS",
            "S",
            "M",
            "L",
            "XL",
            "XXL"
        ],
        "mrp": "1350",
        "price": "999",
        "discount": "25%",
        "available_piece": 10,
        "is_visible": true,
        "images": [
            "/assets/Wshirt1.jpg",
            "",
            "",
            ""
        ],
        "out_of_stock": false,
        "rating": 5,
        "reviews": 200,
        "category": "casual",
        "gender": "female",
        "color": "orange",
        "description": "Lorem ipsum dolor sit amet. Et neque galisum eos ipsum autem est alias neque sed dolorem porro non autem ratione non distinctio quibusdam non sunt quae. Vel Quis error et officia cupiditate est ipsam assumenda qui consequuntur dolores et repudiandae necessitatibus aut internos possimus ut sunt deserunt! Sit quaerat assumenda ut nostrum quia quo ipsa quasi aut animi numquam.Sit provident illum aut sapiente quis et odio maxime et animi doloribus ut quisquam error. ",
        "isSidebar": true
    },
    {
        "name": "Levis",
        "id": 155633,
        "brand_name": "",
        "size": [
            "XS",
            "S",
            "M",
            "L",
            "XL",
            "XXL"
        ],
        "mrp": "2000",
        "price": "1499",
        "discount": "25%",
        "available_piece": 10,
        "is_visible": true,
        "images": [
            "/assets/Wtshirt1.jpg",
            "",
            "",
            ""
        ],
        "out_of_stock": false,
        "rating": 4,
        "reviews": 100,
        "category": "casual",
        "gender": "female",
        "color": "black",
        "description": "Lorem ipsum dolor sit amet. Et neque galisum eos ipsum autem est alias neque sed dolorem porro non autem ratione non distinctio quibusdam non sunt quae. Vel Quis error et officia cupiditate est ipsam assumenda qui consequuntur dolores et repudiandae necessitatibus aut internos possimus ut sunt deserunt! Sit quaerat assumenda ut nostrum quia quo ipsa quasi aut animi numquam.Sit provident illum aut sapiente quis et odio maxime et animi doloribus ut quisquam error. ",
        "isSidebar": true
    },
    {
        "name": "Levis",
        "id": 155633,
        "brand_name": "",
        "size": [
            "XS",
            "S",
            "M",
            "L",
            "XL",
            "XXL"
        ],
        "mrp": "2000",
        "price": "1499",
        "discount": "25%",
        "available_piece": 10,
        "is_visible": true,
        "images": [
            "/assets/Wtshirt1.jpg",
            "",
            "",
            ""
        ],
        "out_of_stock": false,
        "rating": 4,
        "reviews": 100,
        "category": "casual",
        "gender": "female",
        "color": "black",
        "description": "Lorem ipsum dolor sit amet. Et neque galisum eos ipsum autem est alias neque sed dolorem porro non autem ratione non distinctio quibusdam non sunt quae. Vel Quis error et officia cupiditate est ipsam assumenda qui consequuntur dolores et repudiandae necessitatibus aut internos possimus ut sunt deserunt! Sit quaerat assumenda ut nostrum quia quo ipsa quasi aut animi numquam.Sit provident illum aut sapiente quis et odio maxime et animi doloribus ut quisquam error. ",
        "isSidebar": true
    },
    {
        "name": "Levis",
        "id": 155633,
        "brand_name": "",
        "size": [
            "XS",
            "S",
            "M",
            "L",
            "XL",
            "XXL"
        ],
        "mrp": "2000",
        "price": "1499",
        "discount": "25%",
        "available_piece": 10,
        "is_visible": true,
        "images": [
            "/assets/Wtshirt1.jpg",
            "",
            "",
            ""
        ],
        "out_of_stock": false,
        "rating": 4,
        "reviews": 100,
        "category": "casual",
        "gender": "female",
        "color": "black",
        "description": "Lorem ipsum dolor sit amet. Et neque galisum eos ipsum autem est alias neque sed dolorem porro non autem ratione non distinctio quibusdam non sunt quae. Vel Quis error et officia cupiditate est ipsam assumenda qui consequuntur dolores et repudiandae necessitatibus aut internos possimus ut sunt deserunt! Sit quaerat assumenda ut nostrum quia quo ipsa quasi aut animi numquam.Sit provident illum aut sapiente quis et odio maxime et animi doloribus ut quisquam error. ",
        "isSidebar": true
    },
    {
        "name": "Levis",
        "id": 155633,
        "brand_name": "",
        "size": [
            "XS",
            "S",
            "M",
            "L",
            "XL",
            "XXL"
        ],
        "mrp": "2000",
        "price": "1499",
        "discount": "25%",
        "available_piece": 10,
        "is_visible": true,
        "images": [
            "/assets/Wtshirt1.jpg",
            "",
            "",
            ""
        ],
        "out_of_stock": false,
        "rating": 4,
        "reviews": 100,
        "category": "casual",
        "gender": "female",
        "color": "black",
        "description": "Lorem ipsum dolor sit amet. Et neque galisum eos ipsum autem est alias neque sed dolorem porro non autem ratione non distinctio quibusdam non sunt quae. Vel Quis error et officia cupiditate est ipsam assumenda qui consequuntur dolores et repudiandae necessitatibus aut internos possimus ut sunt deserunt! Sit quaerat assumenda ut nostrum quia quo ipsa quasi aut animi numquam.Sit provident illum aut sapiente quis et odio maxime et animi doloribus ut quisquam error. ",
        "isSidebar": true
    },
    {
        "name": "Levis",
        "id": 155633,
        "brand_name": "",
        "size": [
            "XS",
            "S",
            "M",
            "L",
            "XL",
            "XXL"
        ],
        "mrp": "2000",
        "price": "1499",
        "discount": "25%",
        "available_piece": 10,
        "is_visible": true,
        "images": [
            "/assets/Wtshirt1.jpg",
            "",
            "",
            ""
        ],
        "out_of_stock": false,
        "rating": 4,
        "reviews": 100,
        "category": "casual",
        "gender": "female",
        "color": "black",
        "description": "Lorem ipsum dolor sit amet. Et neque galisum eos ipsum autem est alias neque sed dolorem porro non autem ratione non distinctio quibusdam non sunt quae. Vel Quis error et officia cupiditate est ipsam assumenda qui consequuntur dolores et repudiandae necessitatibus aut internos possimus ut sunt deserunt! Sit quaerat assumenda ut nostrum quia quo ipsa quasi aut animi numquam.Sit provident illum aut sapiente quis et odio maxime et animi doloribus ut quisquam error. ",
        "isSidebar": true
    },
    {
        "name": "Levis",
        "id": 155633,
        "brand_name": "",
        "size": [
            "XS",
            "S",
            "M",
            "L",
            "XL",
            "XXL"
        ],
        "mrp": "2000",
        "price": "1499",
        "discount": "25%",
        "available_piece": 10,
        "is_visible": true,
        "images": [
            "/assets/Wtshirt1.jpg",
            "",
            "",
            ""
        ],
        "out_of_stock": false,
        "rating": 4,
        "reviews": 100,
        "category": "casual",
        "gender": "female",
        "color": "black",
        "description": "Lorem ipsum dolor sit amet. Et neque galisum eos ipsum autem est alias neque sed dolorem porro non autem ratione non distinctio quibusdam non sunt quae. Vel Quis error et officia cupiditate est ipsam assumenda qui consequuntur dolores et repudiandae necessitatibus aut internos possimus ut sunt deserunt! Sit quaerat assumenda ut nostrum quia quo ipsa quasi aut animi numquam.Sit provident illum aut sapiente quis et odio maxime et animi doloribus ut quisquam error. ",
        "isSidebar": true
    },
    {
        "name": "Levis",
        "id": 155633,
        "brand_name": "",
        "size": [
            "XS",
            "S",
            "M",
            "L",
            "XL",
            "XXL"
        ],
        "mrp": "2000",
        "price": "1499",
        "discount": "25%",
        "available_piece": 10,
        "is_visible": true,
        "images": [
            "/assets/Wtshirt1.jpg",
            "",
            "",
            ""
        ],
        "out_of_stock": false,
        "rating": 4,
        "reviews": 100,
        "category": "casual",
        "gender": "female",
        "color": "black",
        "description": "Lorem ipsum dolor sit amet. Et neque galisum eos ipsum autem est alias neque sed dolorem porro non autem ratione non distinctio quibusdam non sunt quae. Vel Quis error et officia cupiditate est ipsam assumenda qui consequuntur dolores et repudiandae necessitatibus aut internos possimus ut sunt deserunt! Sit quaerat assumenda ut nostrum quia quo ipsa quasi aut animi numquam.Sit provident illum aut sapiente quis et odio maxime et animi doloribus ut quisquam error. ",
        "isSidebar": true
    },
    {
        "name": "Levis",
        "id": 155633,
        "brand_name": "",
        "size": [
            "XS",
            "S",
            "M",
            "L",
            "XL",
            "XXL"
        ],
        "mrp": "2000",
        "price": "1499",
        "discount": "25%",
        "available_piece": 10,
        "is_visible": true,
        "images": [
            "/assets/Wtshirt1.jpg",
            "",
            "",
            ""
        ],
        "out_of_stock": false,
        "rating": 4,
        "reviews": 100,
        "category": "casual",
        "gender": "female",
        "color": "black",
        "description": "Lorem ipsum dolor sit amet. Et neque galisum eos ipsum autem est alias neque sed dolorem porro non autem ratione non distinctio quibusdam non sunt quae. Vel Quis error et officia cupiditate est ipsam assumenda qui consequuntur dolores et repudiandae necessitatibus aut internos possimus ut sunt deserunt! Sit quaerat assumenda ut nostrum quia quo ipsa quasi aut animi numquam.Sit provident illum aut sapiente quis et odio maxime et animi doloribus ut quisquam error. ",
        "isSidebar": true
    }
]